LICENSE
MANIFEST.in
README.rst
setup.py
django_pardakht.egg-info/PKG-INFO
django_pardakht.egg-info/SOURCES.txt
django_pardakht.egg-info/dependency_links.txt
django_pardakht.egg-info/requires.txt
django_pardakht.egg-info/top_level.txt
pardakht/__init__.py
pardakht/admin.py
pardakht/apps.py
pardakht/decorators.py
pardakht/handler.py
pardakht/models.py
pardakht/urls.py
pardakht/views.py
pardakht/gateways/__init__.py
pardakht/gateways/saman.py
pardakht/gateways/zarinpal.py
pardakht/migrations/0001_initial.py
pardakht/migrations/__init__.py
pardakht/static/pardakht/css/style.css
pardakht/static/pardakht/fonts/BRoya/BRoya.eot
pardakht/static/pardakht/fonts/BRoya/BRoya.ttf
pardakht/static/pardakht/fonts/BRoya/BRoya.woff
pardakht/static/pardakht/fonts/BRoya/ss.eot
pardakht/static/pardakht/fonts/BRoya/ss.ttf
pardakht/static/pardakht/fonts/BRoya/ss.woff
pardakht/static/pardakht/js/jquery.min.js
pardakht/static/pardakht/js/scripts.js
pardakht/static/pardakht/semantic/semantic.js
pardakht/static/pardakht/semantic/semantic.min.js
pardakht/static/pardakht/semantic/semantic.rtl.css
pardakht/static/pardakht/semantic/semantic.rtl.min.css
pardakht/static/pardakht/semantic/components/accordion.js
pardakht/static/pardakht/semantic/components/accordion.min.js
pardakht/static/pardakht/semantic/components/accordion.rtl.css
pardakht/static/pardakht/semantic/components/accordion.rtl.min.css
pardakht/static/pardakht/semantic/components/ad.rtl.css
pardakht/static/pardakht/semantic/components/ad.rtl.min.css
pardakht/static/pardakht/semantic/components/api.js
pardakht/static/pardakht/semantic/components/api.min.js
pardakht/static/pardakht/semantic/components/breadcrumb.rtl.css
pardakht/static/pardakht/semantic/components/breadcrumb.rtl.min.css
pardakht/static/pardakht/semantic/components/button.rtl.css
pardakht/static/pardakht/semantic/components/button.rtl.min.css
pardakht/static/pardakht/semantic/components/card.rtl.css
pardakht/static/pardakht/semantic/components/card.rtl.min.css
pardakht/static/pardakht/semantic/components/checkbox.js
pardakht/static/pardakht/semantic/components/checkbox.min.js
pardakht/static/pardakht/semantic/components/checkbox.rtl.css
