Metadata-Version: 1.1
Name: django-pardakht
Version: 1.4.0
Summary: Django app for connecting to Iranian payment gateways.
Home-page: https://www.github.com/ARKhoshghalb/django-pardakht
Author: Alireza Khoshghalb
Author-email: alirezakhoshghalb@ymail.com
License: MIT License
Platform: UNKNOWN
Classifier: Environment :: Web Environment
Classifier: Framework :: Django
Classifier: Framework :: Django :: 1.11
Classifier: Framework :: Django :: 2.0
Classifier: Intended Audience :: Developers
Classifier: License :: OSI Approved :: MIT License
Classifier: Operating System :: OS Independent
Classifier: Programming Language :: Python
Classifier: Programming Language :: Python :: 3.5
Classifier: Programming Language :: Python :: 3.6
Classifier: Topic :: Internet :: WWW/HTTP
Classifier: Topic :: Internet :: WWW/HTTP :: Dynamic Content
